{"type": "Feature", "id": 12515185, "properties": {"woe:id": 12515185, "woe:parent_id": 379189, "woe:name": "Pilar Airport", "woe:placetype": 14, "woe:placetype_name": "Airport", "woe:lang": "ENG", "iso:country": "PY", "meta:provider": ["geoplanet:7.3.1", "geoplanet:7.3.2", "geoplanet:7.4.0", "geoplanet:7.4.1", "geoplanet:7.5.1", "geoplanet:7.5.2", "geoplanet:7.6.0", "geoplanet:7.8.1", "geoplanet:7.9.0", "geoplanet:7.10.0", "geoplanet:8.0.0", "woeplanet:8.0.0"], "meta:indexed": "2020-08-20T20:21:19.914071", "woe:alias_ENG_V": ["PIL Airport", "PIL"], "meta:updated": "2020-08-22T02:29:00.384029", "woe:hierarchy": {"continent": 24865673, "country": 23424917, "town": 0, "planet": 1, "county": 26810743, "suburb": 0, "state": 2346459, "region": 0, "localadmin": 0}, "woe:timezone_id": 28350737, "woe:hash": "6enx0fw6bu9q", "woe:centroid": [-58.317799, -26.880301], "geom:latitude": -26.880301, "geom:longitude": -58.317799, "geom:hash": "6enx0fw6bu9q", "woe:latitude": -26.880301, "geom:centroid": [-58.317799, -26.880301], "woe:longitude": -58.317799, "woe:repo": "woeplanet-airport-py"}, "geometry": {"coordinates": [-58.317799, -26.880301], "type": "Point"}}